nos/__init__.py
nos/constants.py
nos/exceptions.py
nos/logging.py
nos/protoc.py
nos/version.py
nos/cli/benchmark.py
nos/cli/cli.py
nos/cli/docker.py
nos/cli/hub.py
nos/cli/predict.py
nos/cli/serve_http.py
nos/cli/system.py
nos/cli/utils.py
nos/client/__init__.py
nos/client/grpc.py
nos/common/__init__.py
nos/common/cloudpickle.py
nos/common/exceptions.py
nos/common/git.py
nos/common/metaclass.py
nos/common/profiler.py
nos/common/shm.py
nos/common/spec.py
nos/common/system.py
nos/common/tasks.py
nos/common/types.py
nos/common/io/__init__.py
nos/common/io/video/base.py
nos/common/io/video/opencv.py
nos/executors/__init__.py
nos/executors/ray.py
nos/hub/__init__.py
nos/hub/config.py
nos/managers/__init__.py
nos/managers/model.py
nos/models/__init__.py
nos/models/_noop.py
nos/models/clip.py
nos/models/faster_rcnn.py
nos/models/monodepth.py
nos/models/sam.py
nos/models/stable_diffusion.py
nos/models/whisper.py
nos/models/whisperx.py
nos/models/yolox.py
nos/models/dreambooth/dreambooth.py
nos/models/openmmlab/mmdetection.py
nos/models/super_resolution/__init__.py
nos/models/super_resolution/config.py
nos/models/super_resolution/ldm.py
nos/models/super_resolution/swin2sr.py
nos/proto/nos_service.proto
nos/server/__init__.py
nos/server/_docker.py
nos/server/_runtime.py
nos/server/_service.py
nos/server/train/__init__.py
nos/server/train/_service.py
nos/server/train/config.py
nos/server/train/dreambooth/config.py
autonomi_nos-0.0.10.dist-info/LICENSE
autonomi_nos-0.0.10.dist-info/METADATA
autonomi_nos-0.0.10.dist-info/WHEEL
autonomi_nos-0.0.10.dist-info/entry_points.txt
autonomi_nos-0.0.10.dist-info/top_level.txt
autonomi_nos-0.0.10.dist-info/RECORD
