Metadata-Version: 2.1
Name: autonomi-nos
Version: 0.0.10
Summary: Nitrous oxide system (NOS) for computer-vision.
License: MIT License
Project-URL: Documentation, https://autonomi-ai.github.io/nos/
Project-URL: Source Code, https://github.com/autonomi-ai/nos
Classifier: Development Status :: 3 - Alpha
Classifier: Programming Language :: Python
Classifier: Topic :: Software Development :: Libraries
Classifier: Topic :: Scientific/Engineering :: Artificial Intelligence
Classifier: Topic :: Scientific/Engineering :: Image Processing
Classifier: License :: OSI Approved :: MIT License
Classifier: Programming Language :: Python :: 3
Classifier: Programming Language :: Python :: 3.8
Requires-Python: >=3.7.10
License-File: LICENSE
Requires-Dist: av >=10.0.0
Requires-Dist: cloudpickle >=2.2.1
Requires-Dist: docker >=6.0.0
Requires-Dist: gitpython
Requires-Dist: grpcio-tools <=1.49.1
Requires-Dist: loguru >=0.7.0
Requires-Dist: opencv-python-headless >=4.6.0.66
Requires-Dist: pandas
Requires-Dist: Pillow
Requires-Dist: psutil >=5.9.5
Requires-Dist: py-cpuinfo >=9.0.0
Requires-Dist: pydantic <2.0.0,>=1.10.12
Requires-Dist: rich >=12.5.1
Requires-Dist: tqdm
Requires-Dist: typer >=0.7.0
Requires-Dist: typing-extensions >=4.5.0
Provides-Extra: dev
Requires-Dist: black[jupyter] ==22.3.0 ; extra == 'dev'
Requires-Dist: build ==0.10.0 ; extra == 'dev'
Requires-Dist: pre-commit ==3.2.2 ; extra == 'dev'
Requires-Dist: ruff ==0.0.262 ; extra == 'dev'
Provides-Extra: docs
Requires-Dist: mkdocs >=1.5.2 ; extra == 'docs'
Requires-Dist: mkdocs-blog-plugin ; extra == 'docs'
Requires-Dist: mkdocs-exclude ; extra == 'docs'
Requires-Dist: mkdocs-include-markdown-plugin ; extra == 'docs'
Requires-Dist: mkdocs-material ; extra == 'docs'
Requires-Dist: mkdocs-material-extensions >=1.1 ; extra == 'docs'
Requires-Dist: mkdocs-pymdownx-material-extras ; extra == 'docs'
Requires-Dist: mkdocs-same-dir ; extra == 'docs'
Requires-Dist: mkdocs-table-reader-plugin ; extra == 'docs'
Requires-Dist: mkdocstrings ; extra == 'docs'
Requires-Dist: mkdocstrings-python ; extra == 'docs'
Requires-Dist: mkdocstrings[python] ; extra == 'docs'
Provides-Extra: extras
Requires-Dist: controlnet-aux ==0.0.6 ; extra == 'extras'
Requires-Dist: matplotlib ; extra == 'extras'
Requires-Dist: opencv-contrib-python-headless ; extra == 'extras'
Provides-Extra: server
Requires-Dist: accelerate >0.18.0 ; extra == 'server'
Requires-Dist: diffusers >=0.17.1 ; extra == 'server'
Requires-Dist: huggingface-hub ; extra == 'server'
Requires-Dist: memray ; extra == 'server'
Requires-Dist: pyarrow >=12.0.0 ; extra == 'server'
Requires-Dist: ray[default] >=2.6.1 ; extra == 'server'
Requires-Dist: safetensors >=0.3.0 ; extra == 'server'
Requires-Dist: tabulate ; extra == 'server'
Requires-Dist: timm >=0.9.2 ; extra == 'server'
Requires-Dist: transformers >=4.29.2 ; extra == 'server'
Requires-Dist: torch <2.0.0,>=1.12.1 ; extra == 'server'
Requires-Dist: torchaudio >=0.13.1 ; extra == 'server'
Requires-Dist: torchvision >=0.13.0 ; extra == 'server'
Requires-Dist: controlnet-aux ==0.0.6 ; extra == 'server'
Requires-Dist: matplotlib ; extra == 'server'
Requires-Dist: opencv-contrib-python-headless ; extra == 'server'
Provides-Extra: test
Requires-Dist: pytest ; extra == 'test'
Requires-Dist: pytest-asyncio ; extra == 'test'
Requires-Dist: typeguard ; extra == 'test'
Provides-Extra: torch
Requires-Dist: torch <2.0.0,>=1.12.1 ; extra == 'torch'
Requires-Dist: torchaudio >=0.13.1 ; extra == 'torch'
Requires-Dist: torchvision >=0.13.0 ; extra == 'torch'
